pyperplan/__init__.py
pyperplan/__main__.py
pyperplan/grounding.py
pyperplan/planner.py
pyperplan/task.py
pyperplan/tools.py
pyperplan/heuristics/__init__.py
pyperplan/heuristics/blind.py
pyperplan/heuristics/heuristic_base.py
pyperplan/heuristics/landmarks.py
pyperplan/heuristics/lm_cut.py
pyperplan/heuristics/relaxation.py
pyperplan/pddl/__init__.py
pyperplan/pddl/errors.py
pyperplan/pddl/lisp_iterators.py
pyperplan/pddl/lisp_parser.py
pyperplan/pddl/parser.py
pyperplan/pddl/parser_common.py
pyperplan/pddl/pddl.py
pyperplan/pddl/tree_visitor.py
pyperplan/search/__init__.py
pyperplan/search/a_star.py
pyperplan/search/breadth_first_search.py
pyperplan/search/enforced_hillclimbing_search.py
pyperplan/search/iterative_deepening_search.py
pyperplan/search/minisat.py
pyperplan/search/sat.py
pyperplan/search/searchspace.py
pyperplan-2.1.dist-info/COPYING
pyperplan-2.1.dist-info/METADATA
pyperplan-2.1.dist-info/WHEEL
pyperplan-2.1.dist-info/entry_points.txt
pyperplan-2.1.dist-info/top_level.txt
pyperplan-2.1.dist-info/RECORD
